<?xml version="1.0" encoding="UTF-8"?>
<xml>
	<TowerManager>
		<initialPrice>100</initialPrice>
		<leveledTowers>
			<BottleTower>
				<level>1</level>
				<upgradePrice>180</upgradePrice>
				<sellPrice>80</sellPrice>
				<damage>20</damage>
				<range>1</range>
				<cdTime>1</cdTime>
				<cellImageName>tower_cell_1_1.png</cellImageName>
				<name>Bottle Tower</name>
				<description>Bottle Tower attacks single target.</description></BottleTower>
			<BottleTower>
				<level>2</level>
				<upgradePrice>260</upgradePrice>
				<sellPrice>224</sellPrice>
				<damage>40</damage>
				<range>2</range>
				<cdTime>0.8</cdTime>
				<cellImageName>tower_cell_1_2.png</cellImageName>
				<name>Bottle Tower</name>
				<description>Bottle Tower attacks single target.</description>
			</BottleTower>
			<BottleTower>
				<level>3</level>
				<upgradePrice>0</upgradePrice>
				<sellPrice>432</sellPrice>
				<damage>60</damage>
				<range>3</range>
				<cdTime>0.6</cdTime>
				<cellImageName>tower_cell_1_3.png</cellImageName>
				<name>Bottle Tower</name>
				<description>Bottle Tower attacks single target.</description>
			</BottleTower>
		</leveledTowers>
	</TowerManager>
</xml>